PyCrawlBot/PyCrawlBot.py
PyCrawlBot/__init__.py
PyCrawlBot-0.0.1.dist-info/LICENSE
PyCrawlBot-0.0.1.dist-info/METADATA
PyCrawlBot-0.0.1.dist-info/WHEEL
PyCrawlBot-0.0.1.dist-info/top_level.txt
PyCrawlBot-0.0.1.dist-info/RECORD
